README.md
setup.cfg
setup.py
cectf_server/__init__.py
cectf_server/authentication.py
cectf_server/challenges.py
cectf_server/challenges_admin.py
cectf_server/challenges_files.py
cectf_server/commands.py
cectf_server/database.py
cectf_server/jsconfig.py
cectf_server/models.py
cectf_server/passwords.py
cectf_server/reset.py
cectf_server/test_data.py
cectf_server/users.py
cectf_server.egg-info/PKG-INFO
cectf_server.egg-info/SOURCES.txt
cectf_server.egg-info/dependency_links.txt
cectf_server.egg-info/not-zip-safe
cectf_server.egg-info/requires.txt
cectf_server.egg-info/top_level.txt