Metadata-Version: 1.0
Name: cectf-server
Version: 1.1.5
Summary: Backend for the CECTF
Home-page: https://github.com/cectf/cectf-server
Author: Daniel Chiquito
Author-email: daniel.chiquito@gmail.com
License: UNKNOWN
Platform: UNKNOWN
